hivemind/__init__.py
hivemind/issue.py
hivemind/opinion.py
hivemind/option.py
hivemind/ranking.py
hivemind/state.py
hivemind/utils.py
hivemind/validators.py
hivemind_python-1.0.1.dist-info/licenses/LICENSE
hivemind_python-1.0.1.dist-info/METADATA
hivemind_python-1.0.1.dist-info/WHEEL
hivemind_python-1.0.1.dist-info/top_level.txt
hivemind_python-1.0.1.dist-info/RECORD
