Metadata-Version: 2.4
Name: hivemind-python
Version: 1.0.1
Summary: A Condorcet-style Ranked Choice Voting System that stores all data on IPFS
Home-page: https://github.com/ValyrianTech/hivemind-python
Author: ValyrianTech
License: MIT
Classifier: Development Status :: 5 - Production/Stable
Classifier: Intended Audience :: Developers
Classifier: Operating System :: OS Independent
Classifier: Programming Language :: Python :: 3
Classifier: Programming Language :: Python :: 3.10
Requires-Python: >=3.10
License-File: LICENSE
Requires-Dist: ipfs-dict-chain>=1.1.0
Requires-Dist: python-bitcoinlib>=0.12.2
Provides-Extra: dev
Requires-Dist: pytest>=7.0.0; extra == "dev"
Requires-Dist: pytest-cov>=4.0.0; extra == "dev"
Dynamic: author
Dynamic: classifier
Dynamic: description
Dynamic: description-content-type
Dynamic: home-page
Dynamic: license
Dynamic: license-file
Dynamic: provides-extra
Dynamic: requires-dist
Dynamic: requires-python
Dynamic: summary
